{"response":{"statusCode":"0","winnings":{"dailygrand":{"draw":[{"date":"2026-01-15","day":"Thu","main":{"regular":"11,15,18,26,36","bonus":"02","prizeShares":{"prize":[{"match":"5/5 + GN","winningTickets":"0","amount":[{"@lang":"en","#text":"$1,000 a DAY for LIFE"},{"@lang":"fr","#text":"1 000 $ par JOUR pour LA VIE"}]},{"match":"5/5","winningTickets":"0","amount":[{"@lang":"en","#text":"$25,000 a YEAR for LIFE"},{"@lang":"fr","#text":"25 000 $ par AN pour LA VIE"}]},{"match":"4/5 + GN","winningTickets":"11","amount":[{"@lang":"en","#text":"$1,000.00"},{"@lang":"fr","#text":"1 000,00 $"}]},{"match":"4/5","winningTickets":"57","amount":[{"@lang":"en","#text":"$500.00"},{"@lang":"fr","#text":"500,00 $"}]},{"match":"3/5 + GN","winningTickets":"404","amount":[{"@lang":"en","#text":"$100.00"},{"@lang":"fr","#text":"100,00 $"}]},{"match":"3/5","winningTickets":"2723","amount":[{"@lang":"en","#text":"$20.00"},{"@lang":"fr","#text":"20,00 $"}]},{"match":"2/5 + GN","winningTickets":"5947","amount":[{"@lang":"en","#text":"$10.00"},{"@lang":"fr","#text":"10,00 $"}]},{"match":"1/5 + GN","winningTickets":"29890","amount":[{"@lang":"en","#text":"$4.00"},{"@lang":"fr","#text":"4,00 $"}]},{"match":"0/5 + GN","winningTickets":"47704","amount":[{"@lang":"en","#text":"FREE PLAY"},{"@lang":"fr","#text":"JEU GRATUIT"}]}]}},"encore":{"number":"7616892","prizeShares":{"prize":[{"match":"7616892","winningTickets":"0","amount":"$1,000,000.00"},{"match":"_616892","winningTickets":"0","amount":"$100,000.00"},{"match":"__16892","winningTickets":"0","amount":"$1,000.00"},{"match":"___6892","winningTickets":"6","amount":"$100.00"},{"match":"____892","winningTickets":"93","amount":"$10.00"},{"match":"_____92","winningTickets":"981","amount":"$5.00"},{"match":"______2","winningTickets":"9932","amount":"$2.00"},{"match":"761689_","winningTickets":"0","amount":"$10,000.00"},{"match":"76168__","winningTickets":"0","amount":"$500.00"},{"match":"7616___","winningTickets":"9","amount":"$50.00"},{"match":"761____","winningTickets":"101","amount":"$10.00"},{"match":"76_____","winningTickets":"939","amount":"$5.00"},{"match":"76168_2","winningTickets":"1","amount":"$502.00"},{"match":"7616_92","winningTickets":"0","amount":"$55.00"},{"match":"7616__2","winningTickets":"0","amount":"$52.00"},{"match":"761_892","winningTickets":"0","amount":"$20.00"},{"match":"761__92","winningTickets":"1","amount":"$15.00"},{"match":"761___2","winningTickets":"10","amount":"$12.00"},{"match":"76_6892","winningTickets":"0","amount":"$105.00"},{"match":"76__892","winningTickets":"1","amount":"$15.00"},{"match":"76___92","winningTickets":"6","amount":"$10.00"},{"match":"76____2","winningTickets":"100","amount":"$7.00"}]}}},{"date":"2026-01-12","day":"Mon","main":{"regular":"05,17,19,35,45","bonus":"02","prizeShares":{"prize":[{"match":"5/5 + GN","winningTickets":"0","amount":[{"@lang":"en","#text":"$1,000 a DAY for LIFE"},{"@lang":"fr","#text":"1 000 $ par JOUR pour LA VIE"}]},{"match":"5/5","winningTickets":"0","amount":[{"@lang":"en","#text":"$25,000 a YEAR for LIFE"},{"@lang":"fr","#text":"25 000 $ par AN pour LA VIE"}]},{"match":"4/5 + GN","winningTickets":"17","amount":[{"@lang":"en","#text":"$1,000.00"},{"@lang":"fr","#text":"1 000,00 $"}]},{"match":"4/5","winningTickets":"71","amount":[{"@lang":"en","#text":"$500.00"},{"@lang":"fr","#text":"500,00 $"}]},{"match":"3/5 + GN","winningTickets":"526","amount":[{"@lang":"en","#text":"$100.00"},{"@lang":"fr","#text":"100,00 $"}]},{"match":"3/5","winningTickets":"3332","amount":[{"@lang":"en","#text":"$20.00"},{"@lang":"fr","#text":"20,00 $"}]},{"match":"2/5 + GN","winningTickets":"7465","amount":[{"@lang":"en","#text":"$10.00"},{"@lang":"fr","#text":"10,00 $"}]},{"match":"1/5 + GN","winningTickets":"39064","amount":[{"@lang":"en","#text":"$4.00"},{"@lang":"fr","#text":"4,00 $"}]},{"match":"0/5 + GN","winningTickets":"62296","amount":[{"@lang":"en","#text":"FREE PLAY"},{"@lang":"fr","#text":"JEU GRATUIT"}]}]}},"specialEvent":{"@numDrawn":"5","@numSet":"3","description":[{"@lang":"en","#text":"$25,000 a YEAR for LIFE"},{"@lang":"fr","#text":"25 000 $ par AN pour la VIE"}],"amount":"500000.0","number":[{"regular":"03,11,42,43,49"},{"regular":"06,27,30,35,48"},{"regular":"10,23,33,43,48"}],"prizeShares":{"prize":[{"match":"03 11 42 43 49","winningTickets":"1","amount":[{"@lang":"en","#text":"$25,000 a YEAR for LIFE"},{"@lang":"fr","#text":"25 000 $ par AN pour la VIE"}]},{"match":"06 27 30 35 48","winningTickets":"0","amount":[{"@lang":"en","#text":"$25,000 a YEAR for LIFE"},{"@lang":"fr","#text":"25 000 $ par AN pour la VIE"}]},{"match":"10 23 33 43 48","winningTickets":"0","amount":[{"@lang":"en","#text":"$25,000 a YEAR for LIFE"},{"@lang":"fr","#text":"25 000 $ par AN pour la VIE"}]}]}},"encore":{"number":"8194921","prizeShares":{"prize":[{"match":"8194921","winningTickets":"0","amount":"$1,000,000.00"},{"match":"_194921","winningTickets":"0","amount":"$100,000.00"},{"match":"__94921","winningTickets":"3","amount":"$1,000.00"},{"match":"___4921","winningTickets":"15","amount":"$100.00"},{"match":"____921","winningTickets":"139","amount":"$10.00"},{"match":"_____21","winningTickets":"1333","amount":"$5.00"},{"match":"______1","winningTickets":"13099","amount":"$2.00"},{"match":"819492_","winningTickets":"0","amount":"$10,000.00"},{"match":"81949__","winningTickets":"0","amount":"$500.00"},{"match":"8194___","winningTickets":"11","amount":"$50.00"},{"match":"819____","winningTickets":"125","amount":"$10.00"},{"match":"81_____","winningTickets":"1235","amount":"$5.00"},{"match":"81949_1","winningTickets":"0","amount":"$502.00"},{"match":"8194_21","winningTickets":"0","amount":"$55.00"},{"match":"8194__1","winningTickets":"1","amount":"$52.00"},{"match":"819_921","winningTickets":"0","amount":"$20.00"},{"match":"819__21","winningTickets":"3","amount":"$15.00"},{"match":"819___1","winningTickets":"14","amount":"$12.00"},{"match":"81_4921","winningTickets":"0","amount":"$105.00"},{"match":"81__921","winningTickets":"1","amount":"$15.00"},{"match":"81___21","winningTickets":"9","amount":"$10.00"},{"match":"81____1","winningTickets":"117","amount":"$7.00"}]}}},{"date":"2026-01-08","day":"Thu","main":{"regular":"02,13,19,26,36","bonus":"07","prizeShares":{"prize":[{"match":"5/5 + GN","winningTickets":"0","amount":[{"@lang":"en","#text":"$1,000 a DAY for LIFE"},{"@lang":"fr","#text":"1 000 $ par JOUR pour LA VIE"}]},{"match":"5/5","winningTickets":"0","amount":[{"@lang":"en","#text":"$25,000 a YEAR for LIFE"},{"@lang":"fr","#text":"25 000 $ par AN pour LA VIE"}]},{"match":"4/5 + GN","winningTickets":"21","amount":[{"@lang":"en","#text":"$1,000.00"},{"@lang":"fr","#text":"1 000,00 $"}]},{"match":"4/5","winningTickets":"60","amount":[{"@lang":"en","#text":"$500.00"},{"@lang":"fr","#text":"500,00 $"}]},{"match":"3/5 + GN","winningTickets":"460","amount":[{"@lang":"en","#text":"$100.00"},{"@lang":"fr","#text":"100,00 $"}]},{"match":"3/5","winningTickets":"2779","amount":[{"@lang":"en","#text":"$20.00"},{"@lang":"fr","#text":"20,00 $"}]},{"match":"2/5 + GN","winningTickets":"6979","amount":[{"@lang":"en","#text":"$10.00"},{"@lang":"fr","#text":"10,00 $"}]},{"match":"1/5 + GN","winningTickets":"35077","amount":[{"@lang":"en","#text":"$4.00"},{"@lang":"fr","#text":"4,00 $"}]},{"match":"0/5 + GN","winningTickets":"55157","amount":[{"@lang":"en","#text":"FREE PLAY"},{"@lang":"fr","#text":"JEU GRATUIT"}]}]}},"encore":{"number":"6329960","prizeShares":{"prize":[{"match":"6329960","winningTickets":"0","amount":"$1,000,000.00"},{"match":"_329960","winningTickets":"0","amount":"$100,000.00"},{"match":"__29960","winningTickets":"1","amount":"$1,000.00"},{"match":"___9960","winningTickets":"15","amount":"$100.00"},{"match":"____960","winningTickets":"102","amount":"$10.00"},{"match":"_____60","winningTickets":"1041","amount":"$5.00"},{"match":"______0","winningTickets":"11125","amount":"$2.00"},{"match":"632996_","winningTickets":"1","amount":"$10,000.00"},{"match":"63299__","winningTickets":"2","amount":"$500.00"},{"match":"6329___","winningTickets":"11","amount":"$50.00"},{"match":"632____","winningTickets":"90","amount":"$10.00"},{"match":"63_____","winningTickets":"995","amount":"$5.00"},{"match":"63299_0","winningTickets":"0","amount":"$502.00"},{"match":"6329_60","winningTickets":"0","amount":"$55.00"},{"match":"6329__0","winningTickets":"0","amount":"$52.00"},{"match":"632_960","winningTickets":"0","amount":"$20.00"},{"match":"632__60","winningTickets":"3","amount":"$15.00"},{"match":"632___0","winningTickets":"12","amount":"$12.00"},{"match":"63_9960","winningTickets":"0","amount":"$105.00"},{"match":"63__960","winningTickets":"2","amount":"$15.00"},{"match":"63___60","winningTickets":"12","amount":"$10.00"},{"match":"63____0","winningTickets":"102","amount":"$7.00"}]}}},{"date":"2026-01-05","day":"Mon","main":{"regular":"11,30,38,40,43","bonus":"06","prizeShares":{"prize":[{"match":"5/5 + GN","winningTickets":"0","amount":[{"@lang":"en","#text":"$1,000 a DAY for LIFE"},{"@lang":"fr","#text":"1 000 $ par JOUR pour LA VIE"}]},{"match":"5/5","winningTickets":"0","amount":[{"@lang":"en","#text":"$25,000 a YEAR for LIFE"},{"@lang":"fr","#text":"25 000 $ par AN pour LA VIE"}]},{"match":"4/5 + GN","winningTickets":"10","amount":[{"@lang":"en","#text":"$1,000.00"},{"@lang":"fr","#text":"1 000,00 $"}]},{"match":"4/5","winningTickets":"71","amount":[{"@lang":"en","#text":"$500.00"},{"@lang":"fr","#text":"500,00 $"}]},{"match":"3/5 + GN","winningTickets":"443","amount":[{"@lang":"en","#text":"$100.00"},{"@lang":"fr","#text":"100,00 $"}]},{"match":"3/5","winningTickets":"2726","amount":[{"@lang":"en","#text":"$20.00"},{"@lang":"fr","#text":"20,00 $"}]},{"match":"2/5 + GN","winningTickets":"6380","amount":[{"@lang":"en","#text":"$10.00"},{"@lang":"fr","#text":"10,00 $"}]},{"match":"1/5 + GN","winningTickets":"34626","amount":[{"@lang":"en","#text":"$4.00"},{"@lang":"fr","#text":"4,00 $"}]},{"match":"0/5 + GN","winningTickets":"59268","amount":[{"@lang":"en","#text":"FREE PLAY"},{"@lang":"fr","#text":"JEU GRATUIT"}]}]}},"specialEvent":{"@numDrawn":"5","@numSet":"3","description":[{"@lang":"en","#text":"$25,000 a YEAR for LIFE"},{"@lang":"fr","#text":"25 000 $ par AN pour la VIE"}],"amount":"500000.0","number":[{"regular":"04,24,25,35,45"},{"regular":"14,17,32,34,39"},{"regular":"15,22,26,35,46"}],"prizeShares":{"prize":[{"match":"04 24 25 35 45","winningTickets":"0","amount":[{"@lang":"en","#text":"$25,000 a YEAR for LIFE"},{"@lang":"fr","#text":"25 000 $ par AN pour la VIE"}]},{"match":"14 17 32 34 39","winningTickets":"0","amount":[{"@lang":"en","#text":"$25,000 a YEAR for LIFE"},{"@lang":"fr","#text":"25 000 $ par AN pour la VIE"}]},{"match":"15 22 26 35 46","winningTickets":"0","amount":[{"@lang":"en","#text":"$25,000 a YEAR for LIFE"},{"@lang":"fr","#text":"25 000 $ par AN pour la VIE"}]}]}},"encore":{"number":"8313701","prizeShares":{"prize":[{"match":"8313701","winningTickets":"0","amount":"$1,000,000.00"},{"match":"_313701","winningTickets":"0","amount":"$100,000.00"},{"match":"__13701","winningTickets":"1","amount":"$1,000.00"},{"match":"___3701","winningTickets":"15","amount":"$100.00"},{"match":"____701","winningTickets":"110","amount":"$10.00"},{"match":"_____01","winningTickets":"1227","amount":"$5.00"},{"match":"______1","winningTickets":"12477","amount":"$2.00"},{"match":"831370_","winningTickets":"1","amount":"$10,000.00"},{"match":"83137__","winningTickets":"0","amount":"$500.00"},{"match":"8313___","winningTickets":"13","amount":"$50.00"},{"match":"831____","winningTickets":"116","amount":"$10.00"},{"match":"83_____","winningTickets":"1147","amount":"$5.00"},{"match":"83137_1","winningTickets":"0","amount":"$502.00"},{"match":"8313_01","winningTickets":"0","amount":"$55.00"},{"match":"8313__1","winningTickets":"1","amount":"$52.00"},{"match":"831_701","winningTickets":"0","amount":"$20.00"},{"match":"831__01","winningTickets":"0","amount":"$15.00"},{"match":"831___1","winningTickets":"12","amount":"$12.00"},{"match":"83_3701","winningTickets":"0","amount":"$105.00"},{"match":"83__701","winningTickets":"1","amount":"$15.00"},{"match":"83___01","winningTickets":"8","amount":"$10.00"},{"match":"83____1","winningTickets":"92","amount":"$7.00"}]}}},{"date":"2026-01-01","day":"Thu","main":{"regular":"01,05,07,38,47","bonus":"01","prizeShares":{"prize":[{"match":"5/5 + GN","winningTickets":"0","amount":[{"@lang":"en","#text":"$1,000 a DAY for LIFE"},{"@lang":"fr","#text":"1 000 $ par JOUR pour LA VIE"}]},{"match":"5/5","winningTickets":"0","amount":[{"@lang":"en","#text":"$25,000 a YEAR for LIFE"},{"@lang":"fr","#text":"25 000 $ par AN pour LA VIE"}]},{"match":"4/5 + GN","winningTickets":"6","amount":[{"@lang":"en","#text":"$1,000.00"},{"@lang":"fr","#text":"1 000,00 $"}]},{"match":"4/5","winningTickets":"70","amount":[{"@lang":"en","#text":"$500.00"},{"@lang":"fr","#text":"500,00 $"}]},{"match":"3/5 + GN","winningTickets":"443","amount":[{"@lang":"en","#text":"$100.00"},{"@lang":"fr","#text":"100,00 $"}]},{"match":"3/5","winningTickets":"2533","amount":[{"@lang":"en","#text":"$20.00"},{"@lang":"fr","#text":"20,00 $"}]},{"match":"2/5 + GN","winningTickets":"5985","amount":[{"@lang":"en","#text":"$10.00"},{"@lang":"fr","#text":"10,00 $"}]},{"match":"1/5 + GN","winningTickets":"28727","amount":[{"@lang":"en","#text":"$4.00"},{"@lang":"fr","#text":"4,00 $"}]},{"match":"0/5 + GN","winningTickets":"44004","amount":[{"@lang":"en","#text":"FREE PLAY"},{"@lang":"fr","#text":"JEU GRATUIT"}]}]}},"encore":{"number":"4027232","prizeShares":{"prize":[{"match":"4027232","winningTickets":"0","amount":"$1,000,000.00"},{"match":"_027232","winningTickets":"0","amount":"$100,000.00"},{"match":"__27232","winningTickets":"0","amount":"$1,000.00"},{"match":"___7232","winningTickets":"10","amount":"$100.00"},{"match":"____232","winningTickets":"96","amount":"$10.00"},{"match":"_____32","winningTickets":"1058","amount":"$5.00"},{"match":"______2","winningTickets":"10297","amount":"$2.00"},{"match":"402723_","winningTickets":"0","amount":"$10,000.00"},{"match":"40272__","winningTickets":"1","amount":"$500.00"},{"match":"4027___","winningTickets":"11","amount":"$50.00"},{"match":"402____","winningTickets":"102","amount":"$10.00"},{"match":"40_____","winningTickets":"988","amount":"$5.00"},{"match":"40272_2","winningTickets":"0","amount":"$502.00"},{"match":"4027_32","winningTickets":"0","amount":"$55.00"},{"match":"4027__2","winningTickets":"0","amount":"$52.00"},{"match":"402_232","winningTickets":"0","amount":"$20.00"},{"match":"402__32","winningTickets":"1","amount":"$15.00"},{"match":"402___2","winningTickets":"9","amount":"$12.00"},{"match":"40_7232","winningTickets":"0","amount":"$105.00"},{"match":"40__232","winningTickets":"2","amount":"$15.00"},{"match":"40___32","winningTickets":"5","amount":"$10.00"},{"match":"40____2","winningTickets":"102","amount":"$7.00"}]}}}]}}}}